easyscrape_etsysuggest/__init__.py
easyscrape_etsysuggest/querysuggestions.py
easyscrape_etsysuggest-0.1.1.dist-info/LICENSE
easyscrape_etsysuggest-0.1.1.dist-info/METADATA
easyscrape_etsysuggest-0.1.1.dist-info/WHEEL
easyscrape_etsysuggest-0.1.1.dist-info/top_level.txt
easyscrape_etsysuggest-0.1.1.dist-info/RECORD
